{
  "menu": {
    "entradas": [
      {
        "id": 1,
        "nombre": "Pan De Waffle",
        "descripcionCorta": "Crujiente por fuera, suave por dentro",
        "descripcionLarga": "Disfruta de nuestros deliciosos panes de waffle, perfectos para empezar tu comida con un toque dulce. Servidos con miel y mantequilla.",
        "precio": 8.500,
        "fotografias": ["p1.jpg", "p2.jpeg"]
      },
      {
        "id": 2,
        "nombre": "Aborrajados",
        "descripcionCorta": "Dulce tradición colombiana",
        "descripcionLarga": "Plátanos maduros rellenos de queso, fritos hasta alcanzar la perfección dorada. Un bocado crujiente por fuera y melty por dentro.",
        "precio": 8.500,
        "fotografias": ["p2.jpeg", "p3.jpeg"]
      },
      {
        "id": 3,
        "nombre": "Sachipapas",
        "descripcionCorta": "Combinación clásica y deliciosa",
        "descripcionLarga": "Una mezcla irresistible de salchichas de primera calidad y papas fritas, servida con salsa de la casa. Ideal para compartir.",
        "precio": 8.500,
        "fotografias": ["p3.jpeg", "p5.jpeg"]
      }
    ],
    "platosConFrijol": [
      {
        "id": 5,
        "nombre": "Plato Montañero",
        "descripcionCorta": "Sabor montañero inigualable!",
        "descripcionLarga": "FRIJOLES, ARROZ, CARNES (RES, CERDO, POLLO), COSTILLA Y CHICHARRÓN. ¡UNA EXPERIENCIA IRRESISTIBLE EN CADA BOCADO!.",
        "precio": 32.000,
        "fotografias": ["p6.jpeg", "p5.jpeg"]
      },
      {
        "id": 6,
        "nombre": "Costicazuela",
        "descripcionCorta": "SABORES QUE TE ENAMORARÁN",
        "descripcionLarga": "FRIJOLES, COSTILLITA, HUEVO, MADURO, AGUACATE, MAICITOS Y ARROZ. UNA FIESTA DE SABORES AUTÉNTICOS",
        "precio": 25.000,
        "fotografias": ["p5.jpeg", "p6.jpeg"]
      },
      {
        "id": 7,
        "nombre": "Cazuela de Frijol",
        "descripcionCorta": "TRADICIÓN Y SABORES ÚNICOS!",
        "descripcionLarga": "FRIJOLES, CHICHARRÓN, CARNE DE RES, AGUACATE Y PATACÓN. DELEITE COLOMBIANO AUTÉNTICO.",
        "precio": 25.000,
        "fotografias": ["p7.jpeg", "p8.jpeg"]
      },
      {
        "id": 7,
        "nombre": "BANDEJA PAISA",
        "descripcionCorta": "¡UN FESTÍN IRRESISTIBLE!",
        "descripcionLarga": "FRIJOLES, ARROZ, CHORIZO, CHICHARRÓN, AGUACATE, RES MOLIDA Y HUEVO. SABOR COLOMBIANO EN PERFECTA ARMONÍA.",
        "precio": 25.000,
        "fotografias": ["p7.jpeg", "p8.jpeg"]
      }
    ],
    "delRio": [
      {
        "id": 11,
        "nombre": "Trucha en champiñones",
        "descripcionCorta": "Sabor pescador inigualable",
        "descripcionLarga": "TRUCHA FRITA EN SALSA DE CHAMPIÑONES ACOMPAÑADA DE ARROZ, PAPA FRANCESA, ENSALADA Y MADURO. UN FESTÍN PARA LOS AMANTES DEL PESCADO.",
        "precio": 26.000,
        "fotografias": ["p13.jpeg", "margarita_2.jpg"]
      },
      {
        "id": 12,
        "nombre": "Trucha Frita",
        "descripcionCorta": "SABOR PESCADOR INIGUALABLE.",
        "descripcionLarga": "TRUCHA FRITA ACOMPAÑADA DE ARROZ, PAPA FRANCESA, ENSALADA Y MADURO. UN FESTÍN PARA LOS AMANTES DEL PESCADO.",
        "precio": 24.000,
        "fotografias": ["p13.jpeg", "cerveza_artesanal_2.jpg"]
      },
      {
        "id": 13,
        "nombre": "Tilapia Frita",
        "descripcionCorta": "DELICIA CRUJIENTE Y FRESCA.",
        "descripcionLarga": "TILAPIA FRITA SERVIDA CON ARROZ, PAPA FRANCESA, ENSALADA Y MADURO. UNA COMBINACIÓN DE SABORES QUE TE ENCANTARÁ.",
        "precio": 24.000,
        "fotografias": ["p10.jpeg", "tequila_sunrise_2.jpg"]
      }
    ],
    "carnes": [
      {
        "id": 7,
        "nombre": "Chuleta Valluna",
        "descripcionCorta": "UNA DELICIA VALLUNA IRRESISTIBLE!",
        "descripcionLarga": "CARNE DE POLLO O CERDO APANADA, ACOMPAÑADA DE ARROZ, PAPA FRANCESA Y ENSALADA. UN PLACER CRUJIENTE Y SABROSO.",
        "precio": 25.000,
        "fotografias": ["p4.jpeg", "filete_mignon_2.jpg"]
      },
      {
        "id": 14,
        "nombre": "Costillas BBQ",
        "descripcionCorta": "Sabor ahumado y caramelizado",
        "descripcionLarga": "COSTILLA DE CERDO BAÑADA EN SALSA BBQ, CON MADURO, ARROZ, PAPA FRANCESA ENSALADA. UNA EXPERIENCIA QUE TE HARÁ DESEAR MÁS.",
        "precio": 25.000,
        "fotografias": ["p13.jpeg", "costillas_bbq_2.jpg"]
      },
      {
        "id": 8,
        "nombre": "Pollo a la Parrilla",
        "descripcionCorta": "Sano y delicioso",
        "descripcionLarga": "Pechuga de pollo a la parrilla con hierbas frescas, servido con ensalada y arroz.",
        "precio": 14.99,
        "fotografias": ["p15.jpeg", "pollo_parrilla_2.jpg"]
      }
    
    ],
    "bebidas": [
      {
        "id": 9,
        "nombre": "Margarita",
        "descripcionCorta": "Refrescante y cítrica",
        "descripcionLarga": "Margarita con tequila, triple sec, jugo de limón y sal en el borde del vaso.",
        "precio": 7.99,
        "fotografias": ["margarita_1.jpg", "margarita_2.jpg"]
      },
      {
        "id": 10,
        "nombre": "Cerveza Artesanal",
        "descripcionCorta": "Variedad de sabores",
        "descripcionLarga": "Selección de cervezas artesanales locales y regionales.",
        "precio": 5.99,
        "fotografias": ["cerveza_artesanal_1.jpg", "cerveza_artesanal_2.jpg"]
      },
      {
        "id": 15,
        "nombre": "Tequila Sunrise",
        "descripcionCorta": "Colorido y delicioso",
        "descripcionLarga": "Cóctel con tequila, jugo de naranja y un toque de granadina.",
        "precio": 8.99,
        "fotografias": ["tequila_sunrise_1.jpg", "tequila_sunrise_2.jpg"]
      }
    ]
  }
}
